queue_metrics/__init__.py
queue_metrics/cumulative.py
queue_metrics-0.0.1.dist-info/LICENSE
queue_metrics-0.0.1.dist-info/METADATA
queue_metrics-0.0.1.dist-info/WHEEL
queue_metrics-0.0.1.dist-info/top_level.txt
queue_metrics-0.0.1.dist-info/RECORD
